fungi/__init__.py
fungi/core.py
Fungi-0.1.1.dist-info/WHEEL
Fungi-0.1.1.dist-info/METADATA
Fungi-0.1.1.dist-info/license_files/LICENSE
Fungi-0.1.1.dist-info/RECORD
