Metadata-Version: 2.1
Name: Fungi
Version: 0.1.1
Summary: A set of common utilities for iNotify (based on iNotify Simple) that makes it a little easier to work with
License: GPL-3.0-only
Author-email: Eugene Kovalev <eugene@kovalev.systems>
Requires-Python: >=3.7,<4.0
Classifier: Development Status :: 3 - Alpha
Classifier: Intended Audience :: Developers
Classifier: License :: OSI Approved :: GNU General Public License v3 (GPLv3)
Classifier: Operating System :: OS Independent
Classifier: Programming Language :: Python
Classifier: Programming Language :: Python :: 3.6
Classifier: Programming Language :: Python :: 3.7
Classifier: Programming Language :: Python :: 3.8
Requires-Dist: inotify-simple>=1.3.5
Requires-Dist: psutil<6.0.0,>=5.8.0
Project-URL: documentation, https://gitlab.com/abraxos/fungi
Project-URL: repository, https://gitlab.com/abraxos/fungi
